poulet_py/__init__.py
poulet_py/__init__.pyi
poulet_py/config/__init__.py
poulet_py/config/__init__.pyi
poulet_py/config/logging.py
poulet_py/config/settings.py
poulet_py/converters/__init__.py
poulet_py/converters/__init__.pyi
poulet_py/converters/seq.py
poulet_py/hardware/__init__.py
poulet_py/hardware/__init__.pyi
poulet_py/hardware/camera/__init__.py
poulet_py/hardware/camera/__init__.pyi
poulet_py/hardware/camera/basler.py
poulet_py/hardware/camera/thermal_camera.py
poulet_py/hardware/camera/uvctypes.py
poulet_py/hardware/stimulator/__init__.py
poulet_py/hardware/stimulator/__init__.pyi
poulet_py/hardware/stimulator/arduino.py
poulet_py/hardware/stimulator/julabo.py
poulet_py/hardware/stimulator/qst.py
poulet_py/hardware/triggers/__init__.py
poulet_py/hardware/triggers/__init__.pyi
poulet_py/hardware/triggers/base.py
poulet_py/hardware/triggers/gpio.py
poulet_py/hardware/triggers/keyboard.py
poulet_py/tools/__init__.py
poulet_py/tools/__init__.pyi
poulet_py/tools/generators.py
poulet_py/tools/organizational.py
poulet_py/tools/serializers.py
poulet_py/utils/__init__.py
poulet_py/utils/__init__.pyi
poulet_py/utils/oscilloscope.py
poulet_py/utils/qst.py
poulet_py-0.1.3.dist-info/METADATA
poulet_py-0.1.3.dist-info/WHEEL
poulet_py-0.1.3.dist-info/licenses/LICENSE
poulet_py-0.1.3.dist-info/RECORD
