Metadata-Version: 2.4
Name: poulet_py
Version: 0.1.3
Summary: A library which hosts various neuroscience python methods
Project-URL: Homepage, https://github.com/poulet-lab/poulet_py
Project-URL: Documentation, https://github.com/poulet-lab/poulet_py
Project-URL: Changelog, https://github.com/poulet-lab/poulet_py/release-notes/
Project-URL: Source, https://github.com/poulet-lab/poulet_py
Author-email: Viktor Karamanis <viktor.karamanis@outlook.com>
License-Expression: GPL-3.0-or-later
License-File: LICENSE
Keywords: poulet_py
Classifier: Development Status :: 3 - Alpha
Classifier: License :: OSI Approved :: GNU General Public License v3 or later (GPLv3+)
Classifier: Operating System :: OS Independent
Classifier: Programming Language :: Python
Classifier: Programming Language :: Python :: 3 :: Only
Classifier: Programming Language :: Python :: 3.11
Classifier: Programming Language :: Python :: 3.12
Classifier: Programming Language :: Python :: 3.13
Requires-Python: <3.14,>=3.10
Requires-Dist: deprecated==1.2.*
Requires-Dist: lazy-loader==0.4.*
Requires-Dist: pydantic-settings<2.12,>=2.10
Requires-Dist: pydantic==2.11.*
Requires-Dist: python-dotenv==1.1.*
Requires-Dist: rich==14.1.*
Provides-Extra: all
Requires-Dist: flirpy; extra == 'all'
Requires-Dist: gpiozero==2.0.*; extra == 'all'
Requires-Dist: h5py==3.14.*; extra == 'all'
Requires-Dist: keyboard==0.13.*; extra == 'all'
Requires-Dist: lgpio==0.2.*; extra == 'all'
Requires-Dist: matplotlib==3.10.*; extra == 'all'
Requires-Dist: numpy==2.2.*; extra == 'all'
Requires-Dist: opencv-python==4.12.*; extra == 'all'
Requires-Dist: orjson; extra == 'all'
Requires-Dist: pandas==2.3.*; extra == 'all'
Requires-Dist: pillow==11.3.*; extra == 'all'
Requires-Dist: pypylon==4.2.*; extra == 'all'
Requires-Dist: pyserial==3.5.*; extra == 'all'
Requires-Dist: pythonnet==3.0.*; extra == 'all'
Requires-Dist: pywin32==311; (platform_system == 'Windows') and extra == 'all'
Requires-Dist: scipy==1.16.*; extra == 'all'
Requires-Dist: setuptools==80.9.*; extra == 'all'
Requires-Dist: tqdm==4.67.*; extra == 'all'
Requires-Dist: zstd==1.5.*; extra == 'all'
Provides-Extra: arduino
Requires-Dist: pyserial==3.5.*; extra == 'arduino'
Provides-Extra: camera
Requires-Dist: h5py==3.14.*; extra == 'camera'
Requires-Dist: keyboard==0.13.*; extra == 'camera'
Requires-Dist: matplotlib==3.10.*; extra == 'camera'
Requires-Dist: numpy==2.2.*; extra == 'camera'
Requires-Dist: opencv-python==4.12.*; extra == 'camera'
Requires-Dist: pypylon==4.2.*; extra == 'camera'
Requires-Dist: pythonnet==3.0.*; extra == 'camera'
Requires-Dist: pywin32==311; (platform_system == 'Windows') and extra == 'camera'
Requires-Dist: scipy==1.16.*; extra == 'camera'
Provides-Extra: converters
Requires-Dist: flirpy; extra == 'converters'
Requires-Dist: h5py==3.14.*; extra == 'converters'
Requires-Dist: pandas==2.3.*; extra == 'converters'
Requires-Dist: pillow==11.3.*; extra == 'converters'
Requires-Dist: setuptools==80.9.*; extra == 'converters'
Requires-Dist: tqdm==4.67.*; extra == 'converters'
Requires-Dist: zstd==1.5.*; extra == 'converters'
Provides-Extra: docs
Requires-Dist: ipython==9.4.*; extra == 'docs'
Requires-Dist: pydata-sphinx-theme==0.16.*; extra == 'docs'
Requires-Dist: sphinx-autodoc-typehints==3.2.*; extra == 'docs'
Requires-Dist: sphinx==8.2.*; extra == 'docs'
Provides-Extra: gpio
Requires-Dist: gpiozero==2.0.*; extra == 'gpio'
Requires-Dist: lgpio==0.2.*; extra == 'gpio'
Provides-Extra: hardware
Requires-Dist: gpiozero==2.0.*; extra == 'hardware'
Requires-Dist: h5py==3.14.*; extra == 'hardware'
Requires-Dist: keyboard==0.13.*; extra == 'hardware'
Requires-Dist: lgpio==0.2.*; extra == 'hardware'
Requires-Dist: matplotlib==3.10.*; extra == 'hardware'
Requires-Dist: numpy==2.2.*; extra == 'hardware'
Requires-Dist: opencv-python==4.12.*; extra == 'hardware'
Requires-Dist: pandas==2.3.*; extra == 'hardware'
Requires-Dist: pypylon==4.2.*; extra == 'hardware'
Requires-Dist: pyserial==3.5.*; extra == 'hardware'
Requires-Dist: pythonnet==3.0.*; extra == 'hardware'
Requires-Dist: pywin32==311; (platform_system == 'Windows') and extra == 'hardware'
Requires-Dist: scipy==1.16.*; extra == 'hardware'
Requires-Dist: tqdm==4.67.*; extra == 'hardware'
Provides-Extra: julabo
Requires-Dist: pyserial==3.5.*; extra == 'julabo'
Provides-Extra: osc
Requires-Dist: matplotlib==3.10.*; extra == 'osc'
Requires-Dist: numpy==2.2.*; extra == 'osc'
Requires-Dist: pandas==2.3.*; extra == 'osc'
Provides-Extra: qst
Requires-Dist: pandas==2.3.*; extra == 'qst'
Requires-Dist: pyserial==3.5.*; extra == 'qst'
Requires-Dist: tqdm==4.67.*; extra == 'qst'
Provides-Extra: seq
Requires-Dist: flirpy; extra == 'seq'
Requires-Dist: h5py==3.14.*; extra == 'seq'
Requires-Dist: pandas==2.3.*; extra == 'seq'
Requires-Dist: pillow==11.3.*; extra == 'seq'
Requires-Dist: setuptools==80.9.*; extra == 'seq'
Requires-Dist: tqdm==4.67.*; extra == 'seq'
Requires-Dist: zstd==1.5.*; extra == 'seq'
Provides-Extra: tools
Requires-Dist: orjson; extra == 'tools'
Provides-Extra: triggers
Requires-Dist: gpiozero==2.0.*; extra == 'triggers'
Requires-Dist: lgpio==0.2.*; extra == 'triggers'
Provides-Extra: utils
Requires-Dist: matplotlib==3.10.*; extra == 'utils'
Requires-Dist: numpy==2.2.*; extra == 'utils'
Requires-Dist: pandas==2.3.*; extra == 'utils'
Requires-Dist: pyserial==3.5.*; extra == 'utils'
Requires-Dist: tqdm==4.67.*; extra == 'utils'
